{
  "Title": "Análise de Breaks ",
  "ProcName": "PR_PROPOSTA_R0183",
  "RptName": "R0183",
  "ShowGrid": true,
  "Url": "R0183/PRINT",
  "Filters": [
    {
      "ParameterName": "@Par_Data_Inicio",
      "Type": "Date",
      "Label": "Data Inicio",
      "Search": false,
      "BigQuery": false,
      "Dicionary": "",
      "Value": "",
      "Multiple": false,
      "Class": "col-md-2",
      "Required": true,
      "ArrayValue": []
    },
    {
      "ParameterName": "@Par_Data_Fim",
      "Type": "Date",
      "Label": "Data Término",
      "Search": false,
      "BigQuery": false,
      "Dicionary": "",
      "Value": "",
      "Multiple": false,
      "Required": true,
      "Class": "col-md-2",
      "ArrayValue": []
    },
    {
      "ParameterName": "@Par_Cod_Cliente",
      "Type": "Text",
      "Label": "Cliente",
      "Search": true,
      "BigQuery": true,
      "Dictionary": "Cliente",
      "Value": "",
      "Multiple": false,
      "Class": "col-md-3",
      "ArrayValue": []
    },
    {
      "Class": "row"
    },
    {
      "ParameterName": "@Par_Veiculos",
      "Type": "List",
      "Label": "Veiculos",
      "Search": true,
      "BigQuery": false,
      "Dictionary": "Veiculo",
      "Value": "",
      "Multiple": true,
      "Class": "col-md-2",
      "ArrayValue": []
    },

    {
      "ParameterName": "@Par_Tipo_Midia",
      "Type": "List",
      "Label": "Tipo de Midia",
      "Search": true,
      "BigQuery": false,
      "Dictionary": "TipoMidias",
      "Value": "",
      "Multiple": true,
      "Class": "col-md-2",
      "ArrayValue": []
    },
    {
      "ParameterName": "@Par_Tipo_Comercial",
      "Type": "List",
      "Label": "Tipo de Comercial",
      "Search": true,
      "BigQuery": false,
      "Dictionary": "Tipo_Comercial",
      "Value": "",
      "Multiple": true,
      "Class": "col-md-2",
      "ArrayValue": []
    },
    {
      "ParameterName": "@Par_Programas",
      "Type": "List",
      "Label": "Programa",
      "Search": true,
      "BigQuery": false,
      "Dictionary": "Programa",
      "Value": "",
      "Multiple": true,
      "Class": "col-md-2",
      "ArrayValue": []
    }

  ]
}